llm_memory/__init__.py
llm_memory/memory.py
llm_memory-0.2.1.dist-info/licenses/LICENSE
llm_memory-0.2.1.dist-info/METADATA
llm_memory-0.2.1.dist-info/WHEEL
llm_memory-0.2.1.dist-info/top_level.txt
llm_memory-0.2.1.dist-info/RECORD
