Metadata-Version: 2.4
Name: llm-memory
Version: 0.2.1
Summary: A memory management system for large language models
Home-page: https://github.com/likunpm/llm-memory
Author: likunpm
Author-email: likun2440@gmail.com
Classifier: Programming Language :: Python :: 3
Classifier: License :: OSI Approved :: MIT License
Classifier: Operating System :: OS Independent
Requires-Python: >=3.7
License-File: LICENSE
Requires-Dist: tinydb>=4.7.0
Dynamic: author
Dynamic: author-email
Dynamic: classifier
Dynamic: description
Dynamic: description-content-type
Dynamic: home-page
Dynamic: license-file
Dynamic: requires-dist
Dynamic: requires-python
Dynamic: summary
